telstra_smart_modem/__init__.py
telstra_smart_modem/base.py
telstra_smart_modem/devices.py
telstra_smart_modem/exceptions.py
telstra_smart_modem/modem.py
telstra_smart_modem/srp.py
telstra_smart_modem-1.0.1.dist-info/LICENSE
telstra_smart_modem-1.0.1.dist-info/METADATA
telstra_smart_modem-1.0.1.dist-info/WHEEL
telstra_smart_modem-1.0.1.dist-info/top_level.txt
telstra_smart_modem-1.0.1.dist-info/RECORD
