Metadata-Version: 2.1
Name: telstra-smart-modem
Version: 1.0.1
Summary: Library to retrieve information from a Telstra Smart Modem.
Home-page: https://github.com/hatdz/telstra-smart-modem
Author: hatdz
License: MIT
Platform: UNKNOWN
Classifier: Programming Language :: Python :: 3
Classifier: License :: OSI Approved :: MIT License
Classifier: Operating System :: OS Independent
Requires-Python: >=3.6
Requires-Dist: requests (<3,>=2.22)
Requires-Dist: beautifulsoup4 (<5,>=4.8.2)
